{
  "number": 19,
  "html_url": "https://gitcode.com/cueb-fintech/week03/merge_requests/19",
  "url": "https://gitcode.com/api/v5/repos/cueb-fintech/week03/pulls/19",
  "close_related_issue": 0,
  "prune_branch": false,
  "draft": false,
  "labels": [],
  "user": {
    "id": "67c4f72c882f19112a71fedc",
    "user_id": "4389316",
    "object_id": "67c4f72c882f19112a71fedc",
    "login": "fcl22024110158",
    "name": "怎么吃不饱",
    "state": "active",
    "avatar_url": "https://cdn-img.gitcode.com/fb/dd/f05bd0df0b26937967bcce103e7785b5b74746b489a5893a28d236058af22630.jpg",
    "email": "",
    "name_cn": "",
    "html_url": "https://gitcode.com/fcl22024110158"
  },
  "assignees": [],
  "testers": [],
  "head": {
    "label": "main",
    "ref": "main",
    "sha": "978834a4b1f52ce80ed2f0578ae17d9c88c065ec",
    "user": {
      "id": "67c4f72c882f19112a71fedc",
      "login": "fcl22024110158",
      "name": "怎么吃不饱",
      "state": "active",
      "avatar_url": "https://cdn-img.gitcode.com/fb/dd/f05bd0df0b26937967bcce103e7785b5b74746b489a5893a28d236058af22630.jpg",
      "email": "1900749089@qq.com",
      "name_cn": "",
      "html_url": "https://gitcode.com/fcl22024110158"
    },
    "repo": {
      "id": 4898875,
      "full_path": "fcl22024110158/week03",
      "full_name": "fcl22024110158/week03",
      "human_name": "fcl22024110158 / 第03周打卡",
      "name": "第03周打卡",
      "path": "week03",
      "description": "学生 Fork 此仓库并通过 PR 提交第 3 周学习报告",
      "owner": {
        "id": "67c4f72c882f19112a71fedc",
        "login": "fcl22024110158",
        "name": "怎么吃不饱",
        "state": "active",
        "avatar_url": "https://cdn-img.gitcode.com/fb/dd/f05bd0df0b26937967bcce103e7785b5b74746b489a5893a28d236058af22630.jpg",
        "email": "1900749089@qq.com",
        "name_cn": "",
        "html_url": "https://gitcode.com/fcl22024110158"
      },
      "assigner": {
        "id": "67c4f72c882f19112a71fedc",
        "login": "fcl22024110158",
        "name": "怎么吃不饱",
        "state": "active",
        "avatar_url": "https://cdn-img.gitcode.com/fb/dd/f05bd0df0b26937967bcce103e7785b5b74746b489a5893a28d236058af22630.jpg",
        "email": "1900749089@qq.com",
        "name_cn": "",
        "html_url": "https://gitcode.com/fcl22024110158"
      },
      "internal": false,
      "html_url": "https://gitcode.com/fcl22024110158/week03.git"
    }
  },
  "base": {
    "label": "main",
    "ref": "main",
    "sha": "5ddaabc391fbc7c70f84f469d4bce4f1d6a5df4b",
    "user": {
      "id": "67bbb3b5f510074c7d28739e",
      "login": "mutecamel",
      "name": "mutecamel",
      "state": "active",
      "avatar_url": "https://cdn-img.gitcode.com/fb/ff/f05b2937f9fc3523cea23eb49c7f9042b48968370733119b5b535f820d214aab.jpg",
      "email": "mutecamel@gmail.com",
      "name_cn": "",
      "html_url": "https://gitcode.com/mutecamel"
    },
    "repo": {
      "id": 4830314,
      "full_path": "cueb-fintech/week03",
      "full_name": "cueb-fintech/week03",
      "human_name": "首经贸金融科技实验室 / 第03周打卡",
      "name": "第03周打卡",
      "path": "week03",
      "description": "学生 Fork 此仓库并通过 PR 提交第 3 周学习报告",
      "owner": {
        "id": "67bbb3b5f510074c7d28739e",
        "login": "mutecamel",
        "name": "mutecamel",
        "state": "active",
        "avatar_url": "https://cdn-img.gitcode.com/fb/ff/f05b2937f9fc3523cea23eb49c7f9042b48968370733119b5b535f820d214aab.jpg",
        "email": "mutecamel@gmail.com",
        "name_cn": "",
        "html_url": "https://gitcode.com/mutecamel"
      },
      "assigner": {
        "id": "67bbb3b5f510074c7d28739e",
        "login": "mutecamel",
        "name": "mutecamel",
        "state": "active",
        "avatar_url": "https://cdn-img.gitcode.com/fb/ff/f05b2937f9fc3523cea23eb49c7f9042b48968370733119b5b535f820d214aab.jpg",
        "email": "mutecamel@gmail.com",
        "name_cn": "",
        "html_url": "https://gitcode.com/mutecamel"
      },
      "internal": false,
      "html_url": "https://gitcode.com/cueb-fintech/week03.git"
    }
  },
  "id": 6695376,
  "iid": 19,
  "project_id": 4830314,
  "title": "添加第三周学习报告",
  "body": "添加第三周学习报告",
  "state": "open",
  "assignees_number": 0,
  "testers_number": 0,
  "created_at": "2025-03-20T17:58:36+08:00",
  "updated_at": "2025-03-20T17:58:40+08:00",
  "merged_at": "",
  "closed_at": "",
  "target_branch": "main",
  "source_branch": "main",
  "source_project_id": 4898875,
  "force_remove_source_branch": false,
  "web_url": "https://gitcode.com/cueb-fintech/week03/merge_requests/19",
  "merge_request_type": "MergeRequest",
  "added_lines": 0,
  "removed_lines": 0,
  "diff_refs": {
    "base_sha": "5ddaabc391fbc7c70f84f469d4bce4f1d6a5df4b",
    "head_sha": "978834a4b1f52ce80ed2f0578ae17d9c88c065ec",
    "start_sha": "5ddaabc391fbc7c70f84f469d4bce4f1d6a5df4b"
  },
  "notes": 0,
  "source_git_url": "git@gitcode.com:fcl22024110158/week03.git",
  "can_merge_check": false,
  "mergeable": false,
  "locked": false
}